{
  "generated_at": "2026-03-03T08:01:53.713616Z",
  "window_hours": 24,
  "total_items_analyzed": 54,
  "hot_topics": [
    {
      "keyword": "机器人",
      "category": "板块",
      "count": 6,
      "sample_titles": [
        "银禧科技：目前没有为宇树科技及智元机器人提供产品",
        "高通CEO称机器人技术有望两年内实现规模化",
        "人形机器人卖不动，只能靠租？"
      ]
    },
    {
      "keyword": "人工智能",
      "category": "板块",
      "count": 4,
      "sample_titles": [
        "北京累计已完成217款生成式人工智能服务备案",
        "内容行业最「焦虑」的一个春节",
        "小云雀会成为字节的Higgsfield吗"
      ]
    },
    {
      "keyword": "光伏",
      "category": "板块",
      "count": 2,
      "sample_titles": [
        "光伏巨头储能账面利润近百亿，但赚到钱的为什么是派能、固德威和海博思创？",
        "破局能源焦虑：正泰安能定义户用光伏下半场"
      ]
    },
    {
      "keyword": "医疗",
      "category": "板块",
      "count": 2,
      "sample_titles": [
        "拿下AI制药史上最大IPO，这家公司将挑战阿斯利康等巨头",
        "别只盯着IPO，2026跨国械企并购清单曝光，谁是下一块拼图？"
      ]
    },
    {
      "keyword": "IPO",
      "category": "市场",
      "count": 2,
      "sample_titles": [
        "拿下AI制药史上最大IPO，这家公司将挑战阿斯利康等巨头",
        "别只盯着IPO，2026跨国械企并购清单曝光，谁是下一块拼图？"
      ]
    },
    {
      "keyword": "新能源",
      "category": "板块",
      "count": 1,
      "sample_titles": [
        "光伏巨头储能账面利润近百亿，但赚到钱的为什么是派能、固德威和海博思创？"
      ]
    },
    {
      "keyword": "储能",
      "category": "板块",
      "count": 1,
      "sample_titles": [
        "光伏巨头储能账面利润近百亿，但赚到钱的为什么是派能、固德威和海博思创？"
      ]
    },
    {
      "keyword": "医药",
      "category": "板块",
      "count": 1,
      "sample_titles": [
        "拿下AI制药史上最大IPO，这家公司将挑战阿斯利康等巨头"
      ]
    },
    {
      "keyword": "汽车",
      "category": "板块",
      "count": 1,
      "sample_titles": [
        "起亚2月汽车销量为247401辆，同比下降2.8%。"
      ]
    },
    {
      "keyword": "5G",
      "category": "板块",
      "count": 1,
      "sample_titles": [
        "氪星晚报｜马斯克称第二代星链卫星将提供5G速度的太空互联网服务；调整住宿税，日本京都预计增收132亿日元；卢伟冰：小米今年即将发布全新的机器人产品"
      ]
    },
    {
      "keyword": "涨停",
      "category": "市场",
      "count": 1,
      "sample_titles": [
        "A股三大指数集体收跌，“三桶油”再度涨停"
      ]
    },
    {
      "keyword": "港股",
      "category": "港股",
      "count": 1,
      "sample_titles": [
        "冲刺港交所，“饺子第一股”能否抓住港股对内地餐饮企业的“窗口期”"
      ]
    },
    {
      "keyword": "南向资金",
      "category": "港股",
      "count": 1,
      "sample_titles": [
        "南向资金净买入额达50亿港元"
      ]
    },
    {
      "keyword": "GDP",
      "category": "宏观",
      "count": 1,
      "sample_titles": [
        "新报告：2030年移动产业经济贡献将达全球GDP的8.4%"
      ]
    }
  ]
}