{
  "generated_at": "2026-04-13T03:36:04.269185Z",
  "window_hours": 24,
  "total_items_analyzed": 40,
  "hot_topics": [
    {
      "keyword": "人工智能",
      "category": "板块",
      "count": 2,
      "sample_titles": [
        "曹操出行押注自动驾驶出租车与人工智能将推动其实现上市后首年盈利",
        "工信部：2026年组织编制重点行业“人工智能+质量”应用全景图和转型路线图"
      ]
    },
    {
      "keyword": "机器人",
      "category": "板块",
      "count": 2,
      "sample_titles": [
        "智元机器人、中天科技等在南通成立机器人新公司",
        "一张截图背后：人形机器人赛道的内卷、焦虑与资源争夺战"
      ]
    },
    {
      "keyword": "港股",
      "category": "港股",
      "count": 2,
      "sample_titles": [
        "港股智谱股价盘中突破1000港元",
        "139%的客户在增购：一家中科院AI公司的八年从实验室到港股 | IPO观察"
      ]
    },
    {
      "keyword": "光伏",
      "category": "板块",
      "count": 1,
      "sample_titles": [
        "工信部：开展锂电池、光伏组件等重点产品质量检查"
      ]
    },
    {
      "keyword": "银行",
      "category": "板块",
      "count": 1,
      "sample_titles": [
        "瑞穗银行与VISA将在日本合作推出无现金支付服务"
      ]
    },
    {
      "keyword": "IPO",
      "category": "市场",
      "count": 1,
      "sample_titles": [
        "139%的客户在增购：一家中科院AI公司的八年从实验室到港股 | IPO观察"
      ]
    }
  ]
}